fluspred/Models/AAC_NS2.pkl
fluspred/Models/AAC_PB1F2.pkl
fluspred/Models/DPC_HA.pkl
fluspred/Models/DPC_M1.pkl
fluspred/Models/DPC_M2.pkl
fluspred/Models/DPC_NA.pkl
fluspred/Models/DPC_NP.pkl
fluspred/Models/DPC_NS1.pkl
fluspred/Models/DPC_PA.pkl
fluspred/Models/DPC_PAN155.pkl
fluspred/Models/DPC_PAN182.pkl
fluspred/Models/DPC_PAX.pkl
fluspred/Models/DPC_PB1.pkl
fluspred/Models/DPC_PB1N40.pkl
fluspred/Models/DPC_PB2.pkl
fluspred/Models/Genome_CDK3k.sav
fluspred/python_scripts/__init__.py
fluspred/python_scripts/getDPC.py
fluspred/python_scripts/maintain.py
fluspred/python_scripts/ml_run.py
fluspred/python_scripts/nfeat.py
fluspred-1.1.dist-info/LICENSE.txt
fluspred-1.1.dist-info/METADATA
fluspred-1.1.dist-info/WHEEL
fluspred-1.1.dist-info/entry_points.txt
fluspred-1.1.dist-info/top_level.txt
fluspred-1.1.dist-info/RECORD
