Metadata-Version: 2.1
Name: fluspred
Version: 1.1
Summary: A bioinformatic-ware to predict the zoonotic host tropism of Influenza A virus.
Home-page: https://github.com/raghavagps/fluspred
Requires-Python: >=3.6
License-File: LICENSE.txt
Requires-Dist: numpy (==1.23.5)
Requires-Dist: pandas (==1.2.3)
Requires-Dist: scikit-learn (==1.0.2)
